<?xml version='1.0' encoding='UTF-8'?>
<!DOCTYPE IdentityRequest PUBLIC "sailpoint.dtd" "sailpoint.dtd">
<IdentityRequest completionStatus="Incomplete" endDate="1711455570406" executionStatus="Completed" name="0000000028" priority="Normal" requesterDisplayName="The Administrator" requesterId="0a00020f8d2110f0818d21617fb700ea" source="LCM" state="End" targetClass="sailpoint.object.Identity" targetDisplayName="Suresh.Rajaboina" verified="1712211933038">
  <Attributes>
    <Map>
      <entry key="messages">
        <value>
          <List>
            <Message key="Account created but failed to modify : Failed to update attributes for identity CN=Suresh.Rajaboina,OU=Test,DC=Iconic,DC=com. The specified directory service attribute or value does not exist.&#xa;" type="Warn"/>
            <Message key="Account created but some attributes are not updated properly." type="Error"/>
            <Message key="task_msg_identity_request_verification_timeout" type="Error"/>
          </List>
        </value>
      </entry>
      <entry key="provisionedProject">
        <value>
          <ProvisioningProject identity="Suresh.Rajaboina">
            <Attributes>
              <Map>
                <entry key="disableRetryRequest">
                  <value>
                    <Boolean>true</Boolean>
                  </value>
                </entry>
                <entry key="identityRequestId" value="0000000028"/>
                <entry key="optimisticProvisioning" value="false"/>
                <entry key="requester" value="spadmin"/>
                <entry key="source" value="LCM"/>
              </Map>
            </Attributes>
            <MasterPlan>
              <ProvisioningPlan>
                <AccountRequest application="Active Directory" nativeIdentity="CN=Suresh.Rajaboina,OU=Test,DC=Iconic,DC=com" op="Create">
                  <AttributeRequest name="cn" value="Suresh.Rajaboina"/>
                  <AttributeRequest name="distinguishedName" value="CN=Suresh.Rajaboina,OU=Test,DC=Iconic,DC=com"/>
                  <AttributeRequest name="givenName" value="Suresh"/>
                  <AttributeRequest name="sn" value="Rajaboina"/>
                  <AttributeRequest name="mail" value="suresh.rajaboina"/>
                  <AttributeRequest name="sAMAccountName" value="Suresh.Rajaboina"/>
                  <AttributeRequest name="accountExpiry">
                    <Value>
                      <Date>1711650600000</Date>
                    </Value>
                  </AttributeRequest>
                  <AttributeRequest name="manager" value="CN=Raheem.Shaik,OU=Test,DC=iconic,DC=com"/>
                </AccountRequest>
                <Attributes>
                  <Map>
                    <entry key="identityRequestId" value="0000000028"/>
                    <entry key="requester" value="spadmin"/>
                    <entry key="source" value="LCM"/>
                  </Map>
                </Attributes>
              </ProvisioningPlan>
            </MasterPlan>
            <ProvisioningPlan nativeIdentity="Suresh.Rajaboina" targetIntegration="Active Directory" trackingId="9c38684dae7c466bb51bf13575cc9c86">
              <AccountRequest application="Active Directory" nativeIdentity="CN=Suresh.Rajaboina,OU=Test,DC=Iconic,DC=com" op="Create" targetIntegration="Active Directory">
                <Attributes>
                  <Map>
                    <entry key="provisioningTransactionId" value="0a00030f8e7916b7818e7ab37d650323"/>
                  </Map>
                </Attributes>
                <AttributeRequest name="cn" op="Set" value="Suresh.Rajaboina"/>
                <AttributeRequest name="distinguishedName" op="Set" value="CN=Suresh.Rajaboina,OU=Test,DC=Iconic,DC=com"/>
                <AttributeRequest name="givenName" op="Set" value="Suresh">
                  <ProvisioningResult status="failed"/>
                </AttributeRequest>
                <AttributeRequest name="sn" op="Set" value="Rajaboina">
                  <ProvisioningResult status="failed"/>
                </AttributeRequest>
                <AttributeRequest name="mail" op="Set" value="suresh.rajaboina">
                  <ProvisioningResult status="failed"/>
                </AttributeRequest>
                <AttributeRequest name="sAMAccountName" op="Set" value="Suresh.Rajaboina"/>
                <AttributeRequest name="accountExpiry" op="Set">
                  <Value>
                    <Date>1711650600000</Date>
                  </Value>
                </AttributeRequest>
                <AttributeRequest name="manager" op="Set" value="CN=Raheem.Shaik,OU=Test,DC=iconic,DC=com">
                  <ProvisioningResult status="failed"/>
                </AttributeRequest>
                <AttributeRequest name="objectType" op="Set" value="User"/>
                <AttributeRequest name="password" op="Set">
                  <Attributes>
                    <Map>
                      <entry key="secret" value="true"/>
                    </Map>
                  </Attributes>
                </AttributeRequest>
                <AttributeRequest name="IIQDisabled" op="Set">
                  <Value>
                    <Boolean/>
                  </Value>
                </AttributeRequest>
                <AttributeRequest name="msNPAllowDialin" op="Set" value="Not Set"/>
                <ProvisioningResult status="committed">
                  <Errors>
                    <Message key="Account created but some attributes are not updated properly." type="Error"/>
                  </Errors>
                  <Warnings>
                    <Message key="Account created but failed to modify : Failed to update attributes for identity CN=Suresh.Rajaboina,OU=Test,DC=Iconic,DC=com. The specified directory service attribute or value does not exist.&#xa;" type="Warn"/>
                  </Warnings>
                </ProvisioningResult>
              </AccountRequest>
              <Attributes>
                <Map>
                  <entry key="identityRequestId" value="0000000028"/>
                  <entry key="requester" value="spadmin"/>
                  <entry key="source" value="LCM"/>
                </Map>
              </Attributes>
            </ProvisioningPlan>
          </ProvisioningProject>
        </value>
      </entry>
      <entry key="taskResultId" value="0a00030f8e7916b7818e7ab3624602fe"/>
    </Map>
  </Attributes>
  <RequestItems>
    <IdentityRequestItem application="Active Directory" nativeIdentity="CN=Suresh.Rajaboina,OU=Test,DC=Iconic,DC=com" operation="Create" provisioningEngine="Active Directory" provisioningState="Finished">
      <Attributes>
        <Map>
          <entry key="provisioningPlan">
            <value>
              <ProvisioningPlan trackingId="2e69126151624abd9206bc0619c26f8a">
                <AccountRequest application="Active Directory" nativeIdentity="CN=Suresh.Rajaboina,OU=Test,DC=Iconic,DC=com" op="Create" targetIntegration="Active Directory">
                  <Attributes>
                    <Map>
                      <entry key="provisioningTransactionId" value="0a00030f8e7916b7818e7ab37d650323"/>
                    </Map>
                  </Attributes>
                </AccountRequest>
                <Attributes>
                  <Map>
                    <entry key="source" value="LCM"/>
                  </Map>
                </Attributes>
              </ProvisioningPlan>
            </value>
          </entry>
        </Map>
      </Attributes>
    </IdentityRequestItem>
    <IdentityRequestItem application="Active Directory" approvalState="Finished" compilationStatus="Expansion" expansionCause="ProvisioningPolicy" name="objectType" nativeIdentity="CN=Suresh.Rajaboina,OU=Test,DC=Iconic,DC=com" operation="Set" provisioningEngine="Active Directory" provisioningState="Commited" value="User">
      <Attributes>
        <Map>
          <entry key="expansionInfo" value="Active Directory"/>
          <entry key="managedAttributeType" value="Entitlement"/>
          <entry key="provisioningPlan">
            <value>
              <ProvisioningPlan trackingId="a7cfd1022c4046d1b8aa4c3b97bede92">
                <AccountRequest application="Active Directory" nativeIdentity="CN=Suresh.Rajaboina,OU=Test,DC=Iconic,DC=com" op="Create" targetIntegration="Active Directory">
                  <Attributes>
                    <Map>
                      <entry key="provisioningTransactionId" value="0a00030f8e7916b7818e7ab37d650323"/>
                    </Map>
                  </Attributes>
                  <AttributeRequest name="objectType" op="Set" trackingId="a7cfd1022c4046d1b8aa4c3b97bede92" value="User"/>
                </AccountRequest>
                <Attributes>
                  <Map>
                    <entry key="source" value="LCM"/>
                  </Map>
                </Attributes>
              </ProvisioningPlan>
            </value>
          </entry>
        </Map>
      </Attributes>
    </IdentityRequestItem>
    <IdentityRequestItem application="Active Directory" compilationStatus="Expansion" name="sAMAccountName" nativeIdentity="CN=Suresh.Rajaboina,OU=Test,DC=Iconic,DC=com" operation="Set" provisioningEngine="Active Directory" provisioningState="Finished" value="Suresh.Rajaboina">
      <Attributes>
        <Map>
          <entry key="managedAttributeType" value="Entitlement"/>
          <entry key="provisioningPlan">
            <value>
              <ProvisioningPlan trackingId="91835bf0fd0a436c8a05d328fdaa5f9e">
                <AccountRequest application="Active Directory" nativeIdentity="CN=Suresh.Rajaboina,OU=Test,DC=Iconic,DC=com" op="Create" targetIntegration="Active Directory">
                  <Attributes>
                    <Map>
                      <entry key="provisioningTransactionId" value="0a00030f8e7916b7818e7ab37d650323"/>
                    </Map>
                  </Attributes>
                  <AttributeRequest name="sAMAccountName" op="Set" trackingId="91835bf0fd0a436c8a05d328fdaa5f9e" value="Suresh.Rajaboina"/>
                </AccountRequest>
                <Attributes>
                  <Map>
                    <entry key="source" value="LCM"/>
                  </Map>
                </Attributes>
              </ProvisioningPlan>
            </value>
          </entry>
        </Map>
      </Attributes>
    </IdentityRequestItem>
    <IdentityRequestItem application="Active Directory" approvalState="Finished" compilationStatus="Expansion" name="IIQDisabled" nativeIdentity="CN=Suresh.Rajaboina,OU=Test,DC=Iconic,DC=com" operation="Set" provisioningEngine="Active Directory" provisioningState="Finished" value="false">
      <Attributes>
        <Map>
          <entry key="managedAttributeType" value="Entitlement"/>
          <entry key="provisioningPlan">
            <value>
              <ProvisioningPlan trackingId="2358bf29ebc24974b4903ec27cac78fa">
                <AccountRequest application="Active Directory" nativeIdentity="CN=Suresh.Rajaboina,OU=Test,DC=Iconic,DC=com" op="Create" targetIntegration="Active Directory">
                  <Attributes>
                    <Map>
                      <entry key="provisioningTransactionId" value="0a00030f8e7916b7818e7ab37d650323"/>
                    </Map>
                  </Attributes>
                  <AttributeRequest name="IIQDisabled" op="Set" trackingId="2358bf29ebc24974b4903ec27cac78fa" value="false"/>
                </AccountRequest>
                <Attributes>
                  <Map>
                    <entry key="source" value="LCM"/>
                  </Map>
                </Attributes>
              </ProvisioningPlan>
            </value>
          </entry>
        </Map>
      </Attributes>
    </IdentityRequestItem>
    <IdentityRequestItem application="Active Directory" compilationStatus="Expansion" name="givenName" nativeIdentity="CN=Suresh.Rajaboina,OU=Test,DC=Iconic,DC=com" operation="Set" provisioningEngine="Active Directory" provisioningState="Failed" value="Suresh">
      <Attributes>
        <Map>
          <entry key="managedAttributeType" value="Entitlement"/>
          <entry key="provisioningPlan">
            <value>
              <ProvisioningPlan trackingId="c300e2f3c3de476581ef5d9b2df291da">
                <AccountRequest application="Active Directory" nativeIdentity="CN=Suresh.Rajaboina,OU=Test,DC=Iconic,DC=com" op="Create" targetIntegration="Active Directory">
                  <Attributes>
                    <Map>
                      <entry key="provisioningTransactionId" value="0a00030f8e7916b7818e7ab37d650323"/>
                    </Map>
                  </Attributes>
                  <AttributeRequest name="givenName" op="Set" trackingId="c300e2f3c3de476581ef5d9b2df291da" value="Suresh"/>
                </AccountRequest>
                <Attributes>
                  <Map>
                    <entry key="source" value="LCM"/>
                  </Map>
                </Attributes>
              </ProvisioningPlan>
            </value>
          </entry>
        </Map>
      </Attributes>
    </IdentityRequestItem>
    <IdentityRequestItem application="Active Directory" compilationStatus="Expansion" name="sn" nativeIdentity="CN=Suresh.Rajaboina,OU=Test,DC=Iconic,DC=com" operation="Set" provisioningEngine="Active Directory" provisioningState="Failed" value="Rajaboina">
      <Attributes>
        <Map>
          <entry key="managedAttributeType" value="Entitlement"/>
          <entry key="provisioningPlan">
            <value>
              <ProvisioningPlan trackingId="c30ec7476477442cac07be7e606c582d">
                <AccountRequest application="Active Directory" nativeIdentity="CN=Suresh.Rajaboina,OU=Test,DC=Iconic,DC=com" op="Create" targetIntegration="Active Directory">
                  <Attributes>
                    <Map>
                      <entry key="provisioningTransactionId" value="0a00030f8e7916b7818e7ab37d650323"/>
                    </Map>
                  </Attributes>
                  <AttributeRequest name="sn" op="Set" trackingId="c30ec7476477442cac07be7e606c582d" value="Rajaboina"/>
                </AccountRequest>
                <Attributes>
                  <Map>
                    <entry key="source" value="LCM"/>
                  </Map>
                </Attributes>
              </ProvisioningPlan>
            </value>
          </entry>
        </Map>
      </Attributes>
    </IdentityRequestItem>
    <IdentityRequestItem application="Active Directory" approvalState="Finished" compilationStatus="Expansion" expansionCause="ProvisioningPolicy" name="msNPAllowDialin" nativeIdentity="CN=Suresh.Rajaboina,OU=Test,DC=Iconic,DC=com" operation="Set" provisioningEngine="Active Directory" provisioningState="Finished" value="Not Set">
      <Attributes>
        <Map>
          <entry key="expansionInfo" value="Active Directory"/>
          <entry key="managedAttributeType" value="Entitlement"/>
          <entry key="provisioningPlan">
            <value>
              <ProvisioningPlan trackingId="0137c3bb483f4ac5b445a5bf68413991">
                <AccountRequest application="Active Directory" nativeIdentity="CN=Suresh.Rajaboina,OU=Test,DC=Iconic,DC=com" op="Create" targetIntegration="Active Directory">
                  <Attributes>
                    <Map>
                      <entry key="provisioningTransactionId" value="0a00030f8e7916b7818e7ab37d650323"/>
                    </Map>
                  </Attributes>
                  <AttributeRequest name="msNPAllowDialin" op="Set" trackingId="0137c3bb483f4ac5b445a5bf68413991" value="Not Set"/>
                </AccountRequest>
                <Attributes>
                  <Map>
                    <entry key="source" value="LCM"/>
                  </Map>
                </Attributes>
              </ProvisioningPlan>
            </value>
          </entry>
        </Map>
      </Attributes>
    </IdentityRequestItem>
    <IdentityRequestItem application="Active Directory" compilationStatus="Expansion" name="cn" nativeIdentity="CN=Suresh.Rajaboina,OU=Test,DC=Iconic,DC=com" operation="Set" provisioningEngine="Active Directory" provisioningState="Finished" value="Suresh.Rajaboina">
      <Attributes>
        <Map>
          <entry key="managedAttributeType" value="Entitlement"/>
          <entry key="provisioningPlan">
            <value>
              <ProvisioningPlan trackingId="6092e9a9e14b4585b9a6628d1055b41e">
                <AccountRequest application="Active Directory" nativeIdentity="CN=Suresh.Rajaboina,OU=Test,DC=Iconic,DC=com" op="Create" targetIntegration="Active Directory">
                  <Attributes>
                    <Map>
                      <entry key="provisioningTransactionId" value="0a00030f8e7916b7818e7ab37d650323"/>
                    </Map>
                  </Attributes>
                  <AttributeRequest name="cn" op="Set" trackingId="6092e9a9e14b4585b9a6628d1055b41e" value="Suresh.Rajaboina"/>
                </AccountRequest>
                <Attributes>
                  <Map>
                    <entry key="source" value="LCM"/>
                  </Map>
                </Attributes>
              </ProvisioningPlan>
            </value>
          </entry>
          <entry key="provisioningTransactionId" value="0a00030f8e7916b7818e7ab37d650323"/>
        </Map>
      </Attributes>
    </IdentityRequestItem>
    <IdentityRequestItem application="Active Directory" compilationStatus="Expansion" name="distinguishedName" nativeIdentity="CN=Suresh.Rajaboina,OU=Test,DC=Iconic,DC=com" operation="Set" provisioningEngine="Active Directory" provisioningState="Commited" value="CN=Suresh.Rajaboina,OU=Test,DC=Iconic,DC=com">
      <Attributes>
        <Map>
          <entry key="managedAttributeType" value="Entitlement"/>
          <entry key="provisioningPlan">
            <value>
              <ProvisioningPlan trackingId="b1e25b56e6464ba7ad5b7e78762a4af3">
                <AccountRequest application="Active Directory" nativeIdentity="CN=Suresh.Rajaboina,OU=Test,DC=Iconic,DC=com" op="Create" targetIntegration="Active Directory">
                  <Attributes>
                    <Map>
                      <entry key="provisioningTransactionId" value="0a00030f8e7916b7818e7ab37d650323"/>
                    </Map>
                  </Attributes>
                  <AttributeRequest name="distinguishedName" op="Set" trackingId="b1e25b56e6464ba7ad5b7e78762a4af3" value="CN=Suresh.Rajaboina,OU=Test,DC=Iconic,DC=com"/>
                </AccountRequest>
                <Attributes>
                  <Map>
                    <entry key="source" value="LCM"/>
                  </Map>
                </Attributes>
              </ProvisioningPlan>
            </value>
          </entry>
          <entry key="provisioningTransactionId" value="0a00030f8e7916b7818e7ab37d650323"/>
        </Map>
      </Attributes>
    </IdentityRequestItem>
    <IdentityRequestItem application="Active Directory" compilationStatus="Expansion" name="mail" nativeIdentity="CN=Suresh.Rajaboina,OU=Test,DC=Iconic,DC=com" operation="Set" provisioningEngine="Active Directory" provisioningState="Failed" value="suresh.rajaboina">
      <Attributes>
        <Map>
          <entry key="managedAttributeType" value="Entitlement"/>
          <entry key="provisioningPlan">
            <value>
              <ProvisioningPlan trackingId="a2af88086a724672b1866d43772095e8">
                <AccountRequest application="Active Directory" nativeIdentity="CN=Suresh.Rajaboina,OU=Test,DC=Iconic,DC=com" op="Create" targetIntegration="Active Directory">
                  <Attributes>
                    <Map>
                      <entry key="provisioningTransactionId" value="0a00030f8e7916b7818e7ab37d650323"/>
                    </Map>
                  </Attributes>
                  <AttributeRequest name="mail" op="Set" trackingId="a2af88086a724672b1866d43772095e8" value="suresh.rajaboina"/>
                </AccountRequest>
                <Attributes>
                  <Map>
                    <entry key="source" value="LCM"/>
                  </Map>
                </Attributes>
              </ProvisioningPlan>
            </value>
          </entry>
          <entry key="provisioningTransactionId" value="0a00030f8e7916b7818e7ab37d650323"/>
        </Map>
      </Attributes>
    </IdentityRequestItem>
    <IdentityRequestItem application="Active Directory" compilationStatus="Expansion" name="accountExpiry" nativeIdentity="CN=Suresh.Rajaboina,OU=Test,DC=Iconic,DC=com" operation="Set" provisioningEngine="Active Directory" provisioningState="Unverifiable" value="Thu Mar 28 11:30:00 PDT 2024">
      <Attributes>
        <Map>
          <entry key="managedAttributeType" value="Entitlement"/>
          <entry key="provisioningPlan">
            <value>
              <ProvisioningPlan trackingId="6057e1168ce245bca3d080d0df39012c">
                <AccountRequest application="Active Directory" nativeIdentity="CN=Suresh.Rajaboina,OU=Test,DC=Iconic,DC=com" op="Create" targetIntegration="Active Directory">
                  <Attributes>
                    <Map>
                      <entry key="provisioningTransactionId" value="0a00030f8e7916b7818e7ab37d650323"/>
                    </Map>
                  </Attributes>
                  <AttributeRequest name="accountExpiry" op="Set" trackingId="6057e1168ce245bca3d080d0df39012c" value="Thu Mar 28 11:30:00 PDT 2024"/>
                </AccountRequest>
                <Attributes>
                  <Map>
                    <entry key="source" value="LCM"/>
                  </Map>
                </Attributes>
              </ProvisioningPlan>
            </value>
          </entry>
          <entry key="provisioningTransactionId" value="0a00030f8e7916b7818e7ab37d650323"/>
        </Map>
      </Attributes>
    </IdentityRequestItem>
    <IdentityRequestItem application="Active Directory" compilationStatus="Expansion" name="manager" nativeIdentity="CN=Suresh.Rajaboina,OU=Test,DC=Iconic,DC=com" operation="Set" provisioningEngine="Active Directory" provisioningState="Failed" value="CN=Raheem.Shaik,OU=Test,DC=iconic,DC=com">
      <Attributes>
        <Map>
          <entry key="managedAttributeType" value="Entitlement"/>
          <entry key="provisioningPlan">
            <value>
              <ProvisioningPlan trackingId="c00d9ff0b5b94493b090d00bbb424244">
                <AccountRequest application="Active Directory" nativeIdentity="CN=Suresh.Rajaboina,OU=Test,DC=Iconic,DC=com" op="Create" targetIntegration="Active Directory">
                  <Attributes>
                    <Map>
                      <entry key="provisioningTransactionId" value="0a00030f8e7916b7818e7ab37d650323"/>
                    </Map>
                  </Attributes>
                  <AttributeRequest name="manager" op="Set" trackingId="c00d9ff0b5b94493b090d00bbb424244" value="CN=Raheem.Shaik,OU=Test,DC=iconic,DC=com"/>
                </AccountRequest>
                <Attributes>
                  <Map>
                    <entry key="source" value="LCM"/>
                  </Map>
                </Attributes>
              </ProvisioningPlan>
            </value>
          </entry>
          <entry key="provisioningTransactionId" value="0a00030f8e7916b7818e7ab37d650323"/>
        </Map>
      </Attributes>
    </IdentityRequestItem>
  </RequestItems>
</IdentityRequest>