<?xml version='1.0' encoding='UTF-8'?>
<!DOCTYPE AuditEvent PUBLIC "sailpoint.dtd" "sailpoint.dtd">
<AuditEvent accountName="cn=Test2.Tes2t,ou=Test,dc=iconic,dc=com" action="provision" application="Active Directory" serverHost="WIN-T21N4E0UF24" source="Operations" target="ISIN1005">
  <Attributes>
    <Map>
      <entry key="op">
        <value>
          <ObjectOperation>Disable</ObjectOperation>
        </value>
      </entry>
    </Map>
  </Attributes>
  <String1>Active Directory</String1>
  <String2>failed</String2>
  <String3>Failed to update attribute memberOf Error occurred while setting group membership CN=Domain Users,CN=Users,DC=iconic,DC=com. The server is unwilling to process the request. 0000055E: SvcErr: DSID-031A1260, problem 5003 (WILL_NOT_PERFORM), data 0 . ...</String3>
</AuditEvent>